lindworm/__init__.py
lindworm/ldmArg.py
lindworm/ldmGui.py
lindworm/ldmGuiArt.py
lindworm/ldmGuiNty.py
lindworm/ldmGuiThd.py
lindworm/ldmMD.py
lindworm/ldmOS.py
lindworm/ldmStorage.py
lindworm/ldmStorageFolder.py
lindworm/ldmStorageFolderFrm.py
lindworm/ldmStorageFolderViewFrm.py
lindworm/ldmStorageLine.py
lindworm/ldmStr.py
lindworm/ldmTypes.py
lindworm/ldmWidApp.py
lindworm/ldmWidCore.py
lindworm/ldmWidCoreEvt.py
lindworm/ldmWidFrmAui.py
lindworm/ldmWidImgLst.py
lindworm/ldmWidImgMed.py
lindworm/ldmWidList.py
lindworm/ldmWidPanel.py
lindworm/ldmWidSizeRspWid.py
lindworm/ldmWidThd.py
lindworm/ldmWidTree.py
lindworm/logUtil.py
lindworm/pyGatherMD.py
lindworm/zt_cls.py
lindworm-0.1.1.dist-info/LICENSE
lindworm-0.1.1.dist-info/METADATA
lindworm-0.1.1.dist-info/WHEEL
lindworm-0.1.1.dist-info/entry_points.txt
lindworm-0.1.1.dist-info/top_level.txt
lindworm-0.1.1.dist-info/RECORD
